onfleet/__init__.py
onfleet/_meta.py
onfleet/config.py
onfleet/endpoint.py
onfleet/error.py
onfleet/onfleet.py
onfleet/request.py
pyonfleet-1.5.0.dist-info/licenses/LICENSE
pyonfleet-1.5.0.dist-info/METADATA
pyonfleet-1.5.0.dist-info/WHEEL
pyonfleet-1.5.0.dist-info/top_level.txt
pyonfleet-1.5.0.dist-info/RECORD
