Metadata-Version: 2.4
Name: pyonfleet
Version: 1.5.0
Summary: Onfleet's Python API Wrapper Package
Home-page: http://docs.onfleet.com
Author: James Li
Author-email: support@onfleet.com
License: LICENSE
Classifier: Programming Language :: Python :: 3.7
Classifier: License :: OSI Approved :: MIT License
Classifier: Operating System :: OS Independent
License-File: LICENSE
Requires-Dist: requests
Requires-Dist: ratelimit
Requires-Dist: backoff
Dynamic: author
Dynamic: author-email
Dynamic: classifier
Dynamic: description
Dynamic: description-content-type
Dynamic: home-page
Dynamic: license
Dynamic: license-file
Dynamic: requires-dist
Dynamic: summary
